{
   "page_1_img_1.png": {
      "title": "Impact of Charge Carrier Injection/Extraction Performances in Low\u2010Dimension PEDOT:PSS Organic Electrochemical Transistors",
      "article_name": "C:\\Users\\kvriz\\Desktop\\DataMiningAgents\\outputs\\omiecs_run\\__temp_Low\u2010Dimension-PEDOT-PSS\\Low\u2010Dimension-PEDOT-PSS",
      "image_url": [],
      "figure_name": "page_1_img_1.png",
      "full_caption": "N/A",
      "figure_path": "output\\figures\\page_1_img_1.png",
      "master_images": [
         {
            "classification": "subfigure",
            "confidence": 0.12251568585634232,
            "height": 44,
            "width": 223,
            "geometry": [
               {
                  "x": 2,
                  "y": 0
               },
               {
                  "x": 225,
                  "y": 0
               },
               {
                  "x": 2,
                  "y": 44
               },
               {
                  "x": 225,
                  "y": 44
               }
            ],
            "subfigure_label": {
               "text": "a",
               "geometry": [
                  {
                     "x": 2,
                     "y": 0
                  },
                  {
                     "x": 225,
                     "y": 0
                  },
                  {
                     "x": 2,
                     "y": 44
                  },
                  {
                     "x": 225,
                     "y": 44
                  }
               ]
            },
            "scale_bars": [],
            "caption": [],
            "keywords": []
         }
      ],
      "article_url": [],
      "license": [],
      "open": [],
      "unassigned": {
         "master_images": [],
         "dependent_images": [],
         "inset_images": [],
         "subfigure_labels": [],
         "scale_bar_labels": [],
         "scale_bar_lines": [],
         "captions": [],
         "scale_bar_objects": []
      },
      "caption_delimiter": 0
   },
   "page_2_img_1.png": {
      "title": "Impact of Charge Carrier Injection/Extraction Performances in Low\u2010Dimension PEDOT:PSS Organic Electrochemical Transistors",
      "article_name": "C:\\Users\\kvriz\\Desktop\\DataMiningAgents\\outputs\\omiecs_run\\__temp_Low\u2010Dimension-PEDOT-PSS\\Low\u2010Dimension-PEDOT-PSS",
      "image_url": [],
      "figure_name": "page_2_img_1.png",
      "full_caption": "Figure 1. Bottom contact\u2014Top Gate (BC-TG) OECT in a) staggered or b) planar architectures. c) Microphotograph of OECT with 45% and 55% channel overlap with S&D electrodes, respectively (W = 25 \u03bcm; L = 2.2 \u03bcm; L* = 4 and 4.8 \u03bcm, respectively). The scale bar is worth 50 \u03bcm.",
      "figure_path": "output\\figures\\page_2_img_1.png",
      "master_images": [
         {
            "classification": "subfigure",
            "confidence": 0.9748149514198303,
            "height": 696,
            "width": 676,
            "geometry": [
               {
                  "x": 1369,
                  "y": 2
               },
               {
                  "x": 2045,
                  "y": 2
               },
               {
                  "x": 1369,
                  "y": 698
               },
               {
                  "x": 2045,
                  "y": 698
               }
            ],
            "subfigure_label": {
               "text": "c",
               "geometry": [
                  {
                     "x": 1369,
                     "y": 2
                  },
                  {
                     "x": 2045,
                     "y": 2
                  },
                  {
                     "x": 1369,
                     "y": 698
                  },
                  {
                     "x": 2045,
                     "y": 698
                  }
               ]
            },
            "scale_bars": [
               {
                  "label": {
                     "geometry": [
                        {
                           "x": 1848,
                           "y": 640
                        },
                        {
                           "x": 1848,
                           "y": 671
                        },
                        {
                           "x": 1929,
                           "y": 671
                        },
                        {
                           "x": 1929,
                           "y": 640
                        }
                     ],
                     "text": "50.0 um",
                     "label_confidence": 0.9567362666130066,
                     "box_confidence": 0.9922643899917603,
                     "nm": 50000.0
                  },
                  "geometry": [
                     {
                        "x": 1742,
                        "y": 674
                     },
                     {
                        "x": 1742,
                        "y": 682
                     },
                     {
                        "x": 2034,
                        "y": 682
                     },
                     {
                        "x": 2034,
                        "y": 674
                     }
                  ],
                  "confidence": 0.9416515827178955,
                  "length": 291,
                  "label_line_distance": 506.5
               }
            ],
            "nm_height": 119587.6,
            "nm_width": 116151.2,
            "scale_label": "50.0 um",
            "caption": [],
            "keywords": []
         },
         {
            "classification": "subfigure",
            "confidence": 0.9508605599403381,
            "height": 600,
            "width": 630,
            "geometry": [
               {
                  "x": 0,
                  "y": 5
               },
               {
                  "x": 630,
                  "y": 5
               },
               {
                  "x": 0,
                  "y": 605
               },
               {
                  "x": 630,
                  "y": 605
               }
            ],
            "subfigure_label": {
               "text": "a",
               "geometry": [
                  {
                     "x": 0,
                     "y": 5
                  },
                  {
                     "x": 630,
                     "y": 5
                  },
                  {
                     "x": 0,
                     "y": 605
                  },
                  {
                     "x": 630,
                     "y": 605
                  }
               ]
            },
            "scale_bars": [],
            "caption": [],
            "keywords": []
         },
         {
            "classification": "subfigure",
            "confidence": 0.6611560583114624,
            "height": 594,
            "width": 633,
            "geometry": [
               {
                  "x": 685,
                  "y": 6
               },
               {
                  "x": 1318,
                  "y": 6
               },
               {
                  "x": 685,
                  "y": 600
               },
               {
                  "x": 1318,
                  "y": 600
               }
            ],
            "subfigure_label": {
               "text": "d",
               "geometry": [
                  {
                     "x": 685,
                     "y": 6
                  },
                  {
                     "x": 1318,
                     "y": 6
                  },
                  {
                     "x": 685,
                     "y": 600
                  },
                  {
                     "x": 1318,
                     "y": 600
                  }
               ]
            },
            "scale_bars": [],
            "caption": [],
            "keywords": []
         }
      ],
      "article_url": [],
      "license": [],
      "open": [],
      "unassigned": {
         "master_images": [],
         "dependent_images": [],
         "inset_images": [],
         "subfigure_labels": [],
         "scale_bar_labels": [],
         "scale_bar_lines": [],
         "captions": [],
         "scale_bar_objects": []
      },
      "caption_delimiter": 0
   },
   "page_3_img_1.png": {
      "title": "Impact of Charge Carrier Injection/Extraction Performances in Low\u2010Dimension PEDOT:PSS Organic Electrochemical Transistors",
      "article_name": "C:\\Users\\kvriz\\Desktop\\DataMiningAgents\\outputs\\omiecs_run\\__temp_Low\u2010Dimension-PEDOT-PSS\\Low\u2010Dimension-PEDOT-PSS",
      "image_url": [],
      "figure_name": "page_3_img_1.png",
      "full_caption": "Figure 2. a) Typical output (IDS \u2212 VDS) curve for a planar PEDOT:PSS-based OECT (L = 11 \u03bcm, W = 50 \u03bcm). Gate voltages (VGS) are biased from 0 V to +0.6 V. b) \u03bcOECTC* product (right) and VGS at gm, max (left) as a function of channel length (L) for planar or staggered OECTs.",
      "figure_path": "output\\figures\\page_3_img_1.png",
      "master_images": [
         {
            "classification": "subfigure",
            "confidence": 0.9628918766975403,
            "height": 538,
            "width": 715,
            "geometry": [
               {
                  "x": 785,
                  "y": 4
               },
               {
                  "x": 1500,
                  "y": 4
               },
               {
                  "x": 785,
                  "y": 542
               },
               {
                  "x": 1500,
                  "y": 542
               }
            ],
            "subfigure_label": {
               "text": "b",
               "geometry": [
                  {
                     "x": 785,
                     "y": 4
                  },
                  {
                     "x": 1500,
                     "y": 4
                  },
                  {
                     "x": 785,
                     "y": 542
                  },
                  {
                     "x": 1500,
                     "y": 542
                  }
               ]
            },
            "scale_bars": [],
            "caption": [],
            "keywords": []
         },
         {
            "classification": "subfigure",
            "confidence": 0.9572693705558777,
            "height": 558,
            "width": 769,
            "geometry": [
               {
                  "x": 0,
                  "y": 4
               },
               {
                  "x": 769,
                  "y": 4
               },
               {
                  "x": 0,
                  "y": 562
               },
               {
                  "x": 769,
                  "y": 562
               }
            ],
            "subfigure_label": {
               "text": "a",
               "geometry": [
                  {
                     "x": 0,
                     "y": 4
                  },
                  {
                     "x": 769,
                     "y": 4
                  },
                  {
                     "x": 0,
                     "y": 562
                  },
                  {
                     "x": 769,
                     "y": 562
                  }
               ]
            },
            "scale_bars": [],
            "caption": [],
            "keywords": []
         }
      ],
      "article_url": [],
      "license": [],
      "open": [],
      "unassigned": {
         "master_images": [],
         "dependent_images": [],
         "inset_images": [],
         "subfigure_labels": [],
         "scale_bar_labels": [],
         "scale_bar_lines": [],
         "captions": [],
         "scale_bar_objects": []
      },
      "caption_delimiter": 0
   },
   "page_4_img_1.png": {
      "title": "Impact of Charge Carrier Injection/Extraction Performances in Low\u2010Dimension PEDOT:PSS Organic Electrochemical Transistors",
      "article_name": "C:\\Users\\kvriz\\Desktop\\DataMiningAgents\\outputs\\omiecs_run\\__temp_Low\u2010Dimension-PEDOT-PSS\\Low\u2010Dimension-PEDOT-PSS",
      "image_url": [],
      "figure_name": "page_4_img_1.png",
      "full_caption": "Figure 3. Drain current (IDS) dynamic response according to a pulse Gate bias [\u0394VGS = 0.6 V, \u0394t = 2 ms]: L = 3 \u03bcm; W = 25 \u03bcm; VDS = \u22120.4 V. a) Red and green lines represent fitted curves (exponential dependency) in forward and backward sweeps, respectively. b) Staggered or planar cut-off frequencies according to the channel length (L); W = 25 \u03bcm; VDS = \u22120.1 V; VGS = 0.6 V.",
      "figure_path": "output\\figures\\page_4_img_1.png",
      "master_images": [
         {
            "classification": "subfigure",
            "confidence": 0.9624253511428833,
            "height": 575,
            "width": 719,
            "geometry": [
               {
                  "x": 0,
                  "y": 3
               },
               {
                  "x": 719,
                  "y": 3
               },
               {
                  "x": 0,
                  "y": 578
               },
               {
                  "x": 719,
                  "y": 578
               }
            ],
            "subfigure_label": {
               "text": "a",
               "geometry": [
                  {
                     "x": 0,
                     "y": 3
                  },
                  {
                     "x": 719,
                     "y": 3
                  },
                  {
                     "x": 0,
                     "y": 578
                  },
                  {
                     "x": 719,
                     "y": 578
                  }
               ]
            },
            "scale_bars": [],
            "caption": "Red and green lines represent fitted curves (exponential dependency) in forward and backward sweeps, respectively.",
            "keywords": [
               "Fitted curves",
               "Exponential dependency",
               "Sweeps"
            ]
         },
         {
            "classification": "subfigure",
            "confidence": 0.9580512046813965,
            "height": 577,
            "width": 729,
            "geometry": [
               {
                  "x": 767,
                  "y": 1
               },
               {
                  "x": 1496,
                  "y": 1
               },
               {
                  "x": 767,
                  "y": 578
               },
               {
                  "x": 1496,
                  "y": 578
               }
            ],
            "subfigure_label": {
               "text": "b",
               "geometry": [
                  {
                     "x": 767,
                     "y": 1
                  },
                  {
                     "x": 1496,
                     "y": 1
                  },
                  {
                     "x": 767,
                     "y": 578
                  },
                  {
                     "x": 1496,
                     "y": 578
                  }
               ]
            },
            "scale_bars": [],
            "caption": "Staggered or planar cut-off frequencies according to the channel length (L); W = 25 \u03bcm; VDS = \u22120.1 V; VGS = 0.6 V.",
            "keywords": [
               "Channel length",
               "Cut-off frequencies",
               "Voltage"
            ]
         }
      ],
      "article_url": [],
      "license": [],
      "open": [],
      "unassigned": {
         "master_images": [],
         "dependent_images": [],
         "inset_images": [],
         "subfigure_labels": [],
         "scale_bar_labels": [],
         "scale_bar_lines": [],
         "captions": [],
         "scale_bar_objects": []
      },
      "caption_delimiter": 0
   },
   "page_5_img_1.png": {
      "title": "Impact of Charge Carrier Injection/Extraction Performances in Low\u2010Dimension PEDOT:PSS Organic Electrochemical Transistors",
      "article_name": "C:\\Users\\kvriz\\Desktop\\DataMiningAgents\\outputs\\omiecs_run\\__temp_Low\u2010Dimension-PEDOT-PSS\\Low\u2010Dimension-PEDOT-PSS",
      "image_url": [],
      "figure_name": "page_5_img_1.png",
      "full_caption": "Figure 4. a) Transfer-Length Method (TLM) in the case of planar OECTs (Contact resistance RS/D at L = 0 \u03bcm and A = L+L0= 2.6 \u03bcm; Rcon; W = 0.8 \u03a9 cm) as convergent point). Contact resistance (RS/D) according the Gate voltage (VGS) (at VDS = 0.1 V). b) The dependency of the contact resistance is fitted by an exponential dependency, as RS/D = A exp(B \u00d7 VGS) + C (A, B, C constant parameters are regrouped in Table S1, Supporting Information).",
      "figure_path": "output\\figures\\page_5_img_1.png",
      "master_images": [
         {
            "classification": "subfigure",
            "confidence": 0.9610853791236877,
            "height": 682,
            "width": 739,
            "geometry": [
               {
                  "x": 756,
                  "y": 9
               },
               {
                  "x": 1495,
                  "y": 9
               },
               {
                  "x": 756,
                  "y": 691
               },
               {
                  "x": 1495,
                  "y": 691
               }
            ],
            "subfigure_label": {
               "text": "b",
               "geometry": [
                  {
                     "x": 756,
                     "y": 9
                  },
                  {
                     "x": 1495,
                     "y": 9
                  },
                  {
                     "x": 756,
                     "y": 691
                  },
                  {
                     "x": 1495,
                     "y": 691
                  }
               ]
            },
            "scale_bars": [],
            "caption": "The dependency of the contact resistance is fitted by an exponential dependency, as RS/D = A exp(B \u00d7 VGS) + C (A, B, C constant parameters are regrouped in Table S1, Supporting Information).",
            "keywords": [
               "Contact resistance",
               "Exponential dependency",
               "Fitting"
            ]
         },
         {
            "classification": "subfigure",
            "confidence": 0.9501118659973145,
            "height": 692,
            "width": 709,
            "geometry": [
               {
                  "x": 1,
                  "y": 2
               },
               {
                  "x": 710,
                  "y": 2
               },
               {
                  "x": 1,
                  "y": 694
               },
               {
                  "x": 710,
                  "y": 694
               }
            ],
            "subfigure_label": {
               "text": "a",
               "geometry": [
                  {
                     "x": 1,
                     "y": 2
                  },
                  {
                     "x": 710,
                     "y": 2
                  },
                  {
                     "x": 1,
                     "y": 694
                  },
                  {
                     "x": 710,
                     "y": 694
                  }
               ]
            },
            "scale_bars": [],
            "caption": "Transfer-Length Method (TLM) in the case of planar OECTs (Contact resistance RS/D at L = 0 \u03bcm and A = L+L0= 2.6 \u03bcm; Rcon; W = 0.8 \u03a9 cm) as convergent point). Contact resistance (RS/D) according the Gate voltage (VGS) (at VDS = 0.1 V).",
            "keywords": [
               "Contact resistance",
               "OECTs",
               "TLM"
            ]
         }
      ],
      "article_url": [],
      "license": [],
      "open": [],
      "unassigned": {
         "master_images": [],
         "dependent_images": [],
         "inset_images": [],
         "subfigure_labels": [],
         "scale_bar_labels": [],
         "scale_bar_lines": [],
         "captions": [],
         "scale_bar_objects": []
      },
      "caption_delimiter": 0
   },
   "page_6_img_1.png": {
      "title": "Impact of Charge Carrier Injection/Extraction Performances in Low\u2010Dimension PEDOT:PSS Organic Electrochemical Transistors",
      "article_name": "C:\\Users\\kvriz\\Desktop\\DataMiningAgents\\outputs\\omiecs_run\\__temp_Low\u2010Dimension-PEDOT-PSS\\Low\u2010Dimension-PEDOT-PSS",
      "image_url": [],
      "figure_name": "page_6_img_1.png",
      "full_caption": "N/A",
      "figure_path": "output\\figures\\page_6_img_1.png",
      "master_images": [
         {
            "classification": "subfigure",
            "confidence": 0.9432679414749146,
            "height": 838,
            "width": 1147,
            "geometry": [
               {
                  "x": 903,
                  "y": 0
               },
               {
                  "x": 2050,
                  "y": 0
               },
               {
                  "x": 903,
                  "y": 838
               },
               {
                  "x": 2050,
                  "y": 838
               }
            ],
            "subfigure_label": {
               "text": "b",
               "geometry": [
                  {
                     "x": 903,
                     "y": 0
                  },
                  {
                     "x": 2050,
                     "y": 0
                  },
                  {
                     "x": 903,
                     "y": 838
                  },
                  {
                     "x": 2050,
                     "y": 838
                  }
               ]
            },
            "scale_bars": [],
            "caption": [],
            "keywords": []
         },
         {
            "classification": "subfigure",
            "confidence": 0.9373947978019714,
            "height": 817,
            "width": 923,
            "geometry": [
               {
                  "x": 2,
                  "y": 1
               },
               {
                  "x": 925,
                  "y": 1
               },
               {
                  "x": 2,
                  "y": 818
               },
               {
                  "x": 925,
                  "y": 818
               }
            ],
            "subfigure_label": {
               "text": "a",
               "geometry": [
                  {
                     "x": 2,
                     "y": 1
                  },
                  {
                     "x": 925,
                     "y": 1
                  },
                  {
                     "x": 2,
                     "y": 818
                  },
                  {
                     "x": 925,
                     "y": 818
                  }
               ]
            },
            "scale_bars": [],
            "caption": [],
            "keywords": []
         }
      ],
      "article_url": [],
      "license": [],
      "open": [],
      "unassigned": {
         "master_images": [],
         "dependent_images": [],
         "inset_images": [],
         "subfigure_labels": [],
         "scale_bar_labels": [],
         "scale_bar_lines": [],
         "captions": [],
         "scale_bar_objects": []
      },
      "caption_delimiter": 0
   },
   "page_7_img_1.png": {
      "title": "Impact of Charge Carrier Injection/Extraction Performances in Low\u2010Dimension PEDOT:PSS Organic Electrochemical Transistors",
      "article_name": "C:\\Users\\kvriz\\Desktop\\DataMiningAgents\\outputs\\omiecs_run\\__temp_Low\u2010Dimension-PEDOT-PSS\\Low\u2010Dimension-PEDOT-PSS",
      "image_url": [],
      "figure_name": "page_7_img_1.png",
      "full_caption": "Figure 5. Nonetheless, it is not physically relevant here since \u0394L < 0. It does not explain thus the cut-off frequency saturation we observe in Figure 3b. Moreover, considering that Lconv is acting as an \u201cextension length\u201d in the channel resistance, for L < Lconv = 2.8 \u03bcm, electrode/OMIEC contact is dominating the dynamic response of the OECT. Indeed, below Lconv, cut-off frequency is starting to saturate for L < 3 \u03bcm, as observed in Figure 3b. Through an unprecedented approach, we experimentally prove here the importance to improve the OECTs micro-fabrication, as the layer-to-layer lithography alignment, according to the electrode/OMIEC contact properties. We corroborate that the nature or the morphology of the interfacial layers, their doping states as well as the influence of defects or disorder in such OMIECs are of paramount importance in setting the overall OECTs performances.",
      "figure_path": "output\\figures\\page_7_img_1.png",
      "master_images": [
         {
            "classification": "subfigure",
            "confidence": 1.0,
            "height": 738,
            "width": 800,
            "geometry": [
               {
                  "x": 0,
                  "y": 0
               },
               {
                  "x": 800,
                  "y": 0
               },
               {
                  "x": 0,
                  "y": 738
               },
               {
                  "x": 800,
                  "y": 738
               }
            ],
            "subfigure_label": {
               "text": "0",
               "geometry": [
                  {
                     "x": 0,
                     "y": 0
                  },
                  {
                     "x": 800,
                     "y": 0
                  },
                  {
                     "x": 0,
                     "y": 738
                  },
                  {
                     "x": 800,
                     "y": 738
                  }
               ]
            },
            "scale_bars": [],
            "caption": [],
            "keywords": []
         }
      ],
      "article_url": [],
      "license": [],
      "open": [],
      "unassigned": {
         "master_images": [],
         "dependent_images": [],
         "inset_images": [],
         "subfigure_labels": [],
         "scale_bar_labels": [],
         "scale_bar_lines": [],
         "captions": [],
         "scale_bar_objects": []
      },
      "caption_delimiter": 0
   }
}